{"cameraMode":{"drawMode":0,"name":"Shaded","section":"Shading Mode"},"sceneLighting":false,"audioPlay":false,"sceneViewState":{"m_AlwaysRefresh":false,"showFog":true,"showSkybox":false,"showFlares":true,"showImageEffects":true,"showParticleSystems":true,"showVisualEffectGraphs":true,"m_FxEnabled":true},"in2DMode":false,"pivot":{"x":822.0380249023438,"y":780.8848876953125,"z":107.3477783203125},"rotation":{"x":0.1981445550918579,"y":-0.5946457386016846,"z":0.15424147248268128,"w":0.7638089060783386},"size":10.0,"orthographic":false}